KicadModTree/FileHandler.py
KicadModTree/KicadFileHandler.py
KicadModTree/ModArgparser.py
KicadModTree/Point.py
KicadModTree/PolygonPoints.py
KicadModTree/Vector.py
KicadModTree/__init__.py
KicadModTree/nodes/Footprint.py
KicadModTree/nodes/Node.py
KicadModTree/nodes/__init__.py
KicadModTree/nodes/base/Arc.py
KicadModTree/nodes/base/Circle.py
KicadModTree/nodes/base/Line.py
KicadModTree/nodes/base/Model.py
KicadModTree/nodes/base/Pad.py
KicadModTree/nodes/base/Polygon.py
KicadModTree/nodes/base/Text.py
KicadModTree/nodes/base/__init__.py
KicadModTree/nodes/specialized/ChamferedPad.py
KicadModTree/nodes/specialized/ChamferedPadGrid.py
KicadModTree/nodes/specialized/ExposedPad.py
KicadModTree/nodes/specialized/FilledRect.py
KicadModTree/nodes/specialized/PadArray.py
KicadModTree/nodes/specialized/PolygoneLine.py
KicadModTree/nodes/specialized/RectFill.py
KicadModTree/nodes/specialized/RectLine.py
KicadModTree/nodes/specialized/Rotation.py
KicadModTree/nodes/specialized/Translation.py
KicadModTree/nodes/specialized/__init__.py
KicadModTree/util/__init__.py
KicadModTree/util/kicad_util.py
KicadModTree/util/paramUtil.py
KicadModTree-1.0.3.dist-info/METADATA
KicadModTree-1.0.3.dist-info/RECORD
KicadModTree-1.0.3.dist-info/WHEEL
KicadModTree-1.0.3.dist-info/top_level.txt
