Metadata-Version: 2.1
Name: KicadModTree
Version: 1.0.3
Summary: creating kicad footprints using python scripts
Home-page: https://github.com/pointhi/kicad-footprint-generator
Author: Thomas Pointhuber
Author-email: thomas.pointhuber@gmx.at
License: GPL3+
Platform: UNKNOWN
Classifier: Development Status :: 5 - Production/Stable
Classifier: License :: OSI Approved :: GNU General Public License v3 or later (GPLv3+)
Classifier: Programming Language :: Python
Classifier: Topic :: Scientific/Engineering :: Electronic Design Automation (EDA)
Provides-Extra: test
Provides-Extra: test
